ayaka_test/.git/COMMIT_EDITMSG
ayaka_test/.git/config
ayaka_test/.git/description
ayaka_test/.git/HEAD
ayaka_test/.git/hooks/applypatch-msg.sample
ayaka_test/.git/hooks/commit-msg.sample
ayaka_test/.git/hooks/fsmonitor-watchman.sample
ayaka_test/.git/hooks/post-update.sample
ayaka_test/.git/hooks/pre-applypatch.sample
ayaka_test/.git/hooks/pre-commit.sample
ayaka_test/.git/hooks/pre-merge-commit.sample
ayaka_test/.git/hooks/pre-push.sample
ayaka_test/.git/hooks/pre-rebase.sample
ayaka_test/.git/hooks/pre-receive.sample
ayaka_test/.git/hooks/prepare-commit-msg.sample
ayaka_test/.git/hooks/push-to-checkout.sample
ayaka_test/.git/hooks/update.sample
ayaka_test/.git/index
ayaka_test/.git/info/exclude
ayaka_test/.git/logs/HEAD
ayaka_test/.git/logs/refs/heads/master
ayaka_test/.git/logs/refs/remotes/origin/master
ayaka_test/.git/objects/01/9546091165109ca341922a0d36d155f66cce42
ayaka_test/.git/objects/05/6b18b037695f01fab4df8a7c94c9e74a21ad37
ayaka_test/.git/objects/05/eb906c6368e123c1c6a5601e14edb53448ae12
ayaka_test/.git/objects/06/dbc8392f60c8416d94a4ab48dd334ab50bd90a
ayaka_test/.git/objects/08/d2fd1df6eb99d0a16ff0fc399febf076cbe43d
ayaka_test/.git/objects/0f/9b3ad8e94662493ac0b9152c7967bc03b23d6a
ayaka_test/.git/objects/10/9a6edc35b9c69d970ced4143e67cebe3618483
ayaka_test/.git/objects/13/a76c8d7fdf8bce5c8ffeeee4175913bc07673c
ayaka_test/.git/objects/18/48a1548d4cf688ede7148cfe58321a88d84479
ayaka_test/.git/objects/21/549af9825edd052c673b738484c867ab3e7db1
ayaka_test/.git/objects/25/391ae1f14dd2dae45902ded8d7d31e1296a824
ayaka_test/.git/objects/29/b9ccf5c85febdad1fdcc33851e02d89ca6ef4b
ayaka_test/.git/objects/2b/dc6c438c64732b83d3fe99c9d5e33f59f4b094
ayaka_test/.git/objects/2e/5f847bac3b0cafb2e074c9191700a3aa50a760
ayaka_test/.git/objects/2e/74bc33988c81ebb65a79f90b814de8a6a19da5
ayaka_test/.git/objects/30/b557a21457356bc4a52c7385a915907abf4ccf
ayaka_test/.git/objects/31/86396a8362946876921bd1bae86613448472b5
nonebot_plugin_ayaka_test-0.0.6.dist-info/LICENSE
nonebot_plugin_ayaka_test-0.0.6.dist-info/METADATA
nonebot_plugin_ayaka_test-0.0.6.dist-info/WHEEL
nonebot_plugin_ayaka_test-0.0.6.dist-info/RECORD
